pycons/__init__.py
pycons/asciicons.py
pycons/favicon.py
pycons/font_providers/__init__.py
pycons/font_providers/base.py
pycons/font_providers/models.py
pycons/font_providers/providers.py
pycons/font_providers/registry.py
pycons/functional.py
pycons/iconify/__init__.py
pycons/iconify/api.py
pycons/iconify/iconify.py
pycons/iconify/iconify_types.py
pycons/py.typed
pycons/utils.py
pycons-1.0.0.dist-info/WHEEL
pycons-1.0.0.dist-info/METADATA
pycons-1.0.0.dist-info/RECORD
