Metadata-Version: 2.3
Name: pycons
Version: 1.0.0
Summary: Icon utilities (Material Design icons & similar)
Keywords: 
Author: Philipp Temminghoff
Author-email: Philipp Temminghoff <philipptemminghoff@googlemail.com>
License: MIT License
Classifier: Development Status :: 4 - Beta
Classifier: Intended Audience :: Developers
Classifier: Operating System :: OS Independent
Classifier: Programming Language :: Python :: 3
Classifier: Programming Language :: Python :: 3 :: Only
Classifier: Programming Language :: Python :: 3.12
Classifier: Programming Language :: Python :: 3.13
Classifier: Programming Language :: Python :: 3.14
Classifier: Topic :: Documentation
Classifier: Topic :: Software Development
Classifier: Topic :: Utilities
Classifier: Typing :: Typed
Requires-Dist: anyenv>=0.2.0
Requires-Dist: appdirs>=1.4.4
Requires-Dist: hishel>=0.1.1
Requires-Dist: httpx>=0.28.1
Requires-Python: >=3.13
Project-URL: Code coverage, https://app.codecov.io/gh/phil65/pycons
Project-URL: Discussions, https://github.com/phil65/pycons/discussions
Project-URL: Documentation, https://phil65.github.io/pycons/
Project-URL: Issues, https://github.com/phil65/pycons/issues
Project-URL: Source, https://github.com/phil65/pycons
